Workbook

Sheet Inputs
A1: Hackles Day in a Box: inputs
A2: © 2026 Competence Collective. Lesson text and teaching materials CC BY-NC 4.0. The Hackles name, logos, characters and artwork are not covered by that license: print and share them unaltered for classroom and family use; any other use needs written permission. [VERIFY with counsel]
A3: Type your numbers in the yellow cells. Unit costs on the Budget sheet are placeholders, not quotes: replace them with prices from your own vendors and district. Costs vary by region and year. No names or student data belong in this workbook.
A4: Event name or date (optional) | B4: Hackles Day
A5: Students attending | B5: 300
A6: Family members attending family night | B6: 150
A7: Volunteers and staff helping | B7: 12
A8: Number of stations | B8: 8
A9: Interpreter hours | B9: 4
A10: Childcare staff-hours | B10: 6
A11: Contingency (percent of subtotal) | B11: 0.1

Sheet Budget
A1: Hackles Day in a Box: budget
A2: © 2026 Competence Collective. Lesson text and teaching materials CC BY-NC 4.0. The Hackles name, logos, characters and artwork are not covered by that license: print and share them unaltered for classroom and family use; any other use needs written permission. [VERIFY with counsel]
A3: Yellow cells are yours to change. Unit costs are placeholders. 'Low-cost' assumes classroom supplies, volunteer help and donated items that your policy allows. Do not accept sponsorship that brands lessons or collects student data.
A5: Item | B5: Basis | C5: Quantity | D5: Unit | E5: Standard unit cost ($) | F5: Standard total ($) | G5: Low-cost unit cost ($) | H5: Low-cost total ($) | I5: In-kind or donated ($, enter) | J5: Net standard ($) | K5: Notes
A6: Printing: student passports | B6: 4 pages per student | C6: =Inputs!$B$5*4 | D6: page | E6: 0.06 | F6: =C6*E6 | G6: 0.03 | H6: =C6*G6 | I6: 0 | J6: =F6-I6 | K6: Passport: a folded paper with a stamp space per station
A7: Printing: family handouts | B7: 6 pages per family attending | C7: =Inputs!$B$6*6 | D7: page | E7: 0.06 | F7: =C7*E7 | G7: 0.03 | H7: =C7*G7 | I7: 0 | J7: =F7-I7 | K7: Conversation starters, code word guide, tech agreement, what-to-do page
A8: Printing: station cards, signs, hunt sheets | B8: 25 pages per station | C8: =Inputs!$B$8*25 | D8: page | E8: 0.06 | F8: =C8*E8 | G8: 0.03 | H8: =C8*G8 | I8: 0 | J8: =F8-I8 | K8: Use classroom copier where allowed
A9: Certificates (cardstock) | B9: 1 per student | C9: =Inputs!$B$5 | D9: sheet | E9: 0.25 | F9: =C9*E9 | G9: 0.05 | H9: =C9*G9 | I9: 0 | J9: =F9-I9 | K9: Cardstock or plain paper
A10: Craft and station supplies | B10: per 100 students | C10: =Inputs!$B$5/100 | D10: per 100 | E10: 60 | F10: =C10*E10 | G10: 15 | H10: =C10*G10 | I10: 0 | J10: =F10-I10 | K10: Paper, markers, sticky notes, index cards, tape, timers. Use classroom stock for the low-cost column
A11: Stamps, stickers, ribbons | B11: per student | C11: =Inputs!$B$5 | D11: student | E11: 0.4 | F11: =C11*E11 | G11: 0.1 | H11: =C11*G11 | I11: 0 | J11: =F11-I11 | K11: No sponsor branding. No items that require a sign-up
A12: Volunteer name badges and lanyards | B12: per volunteer | C12: =Inputs!$B$7 | D12: volunteer | E12: 3 | F12: =C12*E12 | G12: 0 | H12: =C12*G12 | I12: 0 | J12: =F12-I12 | K12: Reuse school lanyards in the low-cost column
A13: Food and drink (family corner) | B13: per family attending | C13: =Inputs!$B$6 | D13: family | E13: 2.5 | F13: =C13*E13 | G13: 0 | H13: =C13*G13 | I13: 0 | J13: =F13-I13 | K13: Optional
A14: Translation and interpreters | B14: hours | C14: =Inputs!$B$9 | D14: hour | E14: 60 | F14: =C14*E14 | G14: 0 | H14: =C14*G14 | I14: 0 | J14: =F14-I14 | K14: Qualified interpreters or bilingual staff. Do not use machine translation alone for safety wording
A15: Childcare during family night | B15: staff hours | C15: =Inputs!$B$10 | D15: hour | E15: 15 | F15: =C15*E15 | G15: 0 | H15: =C15*G15 | I15: 0 | J15: =F15-I15 | K15: Only if offered; follow your child-supervision policy
A16: Posters and signage | B16: lump sum | C16: =1 | D16: event | E16: 40 | F16: =C16*E16 | G16: 10 | H16: =C16*G16 | I16: 0 | J16: =F16-I16 | K16: Welcome banner, station signs, Counselor Corner, Tell Someone Wall, accessibility signs
A17: First aid, tissues, sanitizer | B17: lump sum | C17: =1 | D17: event | E17: 20 | F17: =C17*E17 | G17: 5 | H17: =C17*G17 | I17: 0 | J17: =F17-I17 | K17: Use the school's existing kit where possible
A18: Thank-you items for volunteers and staff | B18: per volunteer | C18: =Inputs!$B$7 | D18: volunteer | E18: 3 | F18: =C18*E18 | G18: 1 | H18: =C18*G18 | I18: 0 | J18: =F18-I18 | K18: A card and a small item. Check your gift policy
A20: Subtotal | F20: =SUM(F6:F18) | H20: =SUM(H6:H18) | I20: =SUM(I6:I18) | J20: =SUM(J6:J18)
A21: Contingency | F21: =F20*Inputs!$B$11 | H21: =H20*Inputs!$B$11 | J21: =J20*Inputs!$B$11
A22: TOTAL | F22: =F20+F21 | H22: =H20+H21 | J22: =J20+J21
A23: Cost per student attending | F23: =IF(Inputs!$B$5=0,"",F22/Inputs!$B$5) | H23: =IF(Inputs!$B$5=0,"",H22/Inputs!$B$5) | J23: =IF(Inputs!$B$5=0,"",J22/Inputs!$B$5)
A26: Funding source (type it):
A27: Approved by and date (type it):
